{
  "Firma Standard": {
    "scale": 0.5,
    "position": "bottom-right",
    "opacity": 0.8,
    "watermark_path": "sign.png",
    "description": "Firma standard in basso a destra"
  },
  "Firma Piccola": {
    "scale": 0.3,
    "position": "bottom-right", 
    "opacity": 0.6,
    "watermark_path": "sign.png",
    "description": "Firma piccola e discreta"
  },
  "Firma Ufficiale": {
    "scale": 0.7,
    "position": "bottom-left",
    "opacity": 1.0,
    "watermark_path": "signAL.png",
    "description": "Firma grande per documenti ufficiali"
  },
  "Firma Alto Sinistra": {
    "scale": 0.4,
    "position": "top-left",
    "opacity": 0.7,
    "watermark_path": "sign.png",
    "description": "Firma piccola in alto a sinistra"
  },
  "Watermark Trasparente": {
    "scale": 0.8,
    "position": "top-right",
    "opacity": 0.3,
    "watermark_path": "sign.png",
    "description": "Watermark grande e molto trasparente"
  }
}
